<mods xmlns='http://www.loc.gov/mods/v3' xmlns:xsi='http://www.w3.org/2001/XMLSchema-instance' xsi:schemaLocation='http://www.loc.gov/mods/v3 http://www.loc.gov/standards/mods/v3/mods-3-4.xsd'>
<identifier type='local'>prd.custord.070103a</identifier>
<titleInfo><title>With William Burroughs: a report from the bunker: Burroughs comes across a variety of the yage vine in the jungle..., p. 113, image</title></titleInfo>
<name type='personal'><namePart>Bockris, Victor</namePart></name>
<name type='personal'><namePart>Burroughs, William</namePart></name>
<typeOfResource>still image</typeOfResource>
<physicalDescription><form authority='marcform'>electronic</form>
<form authority='aat'>photographs</form>
<extent>1 item</extent>
<reformattingQuality>access</reformattingQuality>
<internetMediaType>image/tiff</internetMediaType>
<digitalOrigin>reformatted digital</digitalOrigin>
</physicalDescription>
<originInfo><dateIssued keyDate='yes'>1996</dateIssued></originInfo>
<location><physicalLocation authority='marcorg'>NNC</physicalLocation>
<physicalLocation>General Collections, Columbia University Libraries</physicalLocation>
</location>
<relatedItem type='host' displayLabel='Project'><titleInfo><title>Customer Order Collection</title></titleInfo></relatedItem>
<note>Original PRD customer order number: 070103</note>
<accessCondition type='useAndReproduction'>Columbia Libraries Staff Use Only</accessCondition>
<recordInfo><recordCreationDate encoding='w3cdtf'>2010-09-16</recordCreationDate><recordContentSource authority='marcorg'>NNC</recordContentSource><languageOfCataloging><languageTerm type='code' authority='iso639-2b'>eng</languageTerm></languageOfCataloging><recordOrigin>From PRD customer order database, edited to conform to the DLF Implementation Guidelines for Shareable MODS Records, Version 1.1.</recordOrigin></recordInfo> </mods>